[
  {
    "name": "A to Z Silver Multivitamin & Multimineral",
    "genericName": "A to Z Silver",
    "strength": "100 mg",
    "manufacturer": "Pharmik Laboratories Ltd.",
    "brand": "Pharmik",
    "category": "Multivitamin",
    "batchNumber": "",
    "expiryDate": null,
    "mrp": 0,
    "quantity": 0
  },
  {
    "name": "A-B1",
    "genericName": "Thiamine Hydrochloride",
    "strength": "100 mg",
    "manufacturer": "ACME Laboratories Ltd.",
    "brand": "ACME",
    "category": "Vitamin B1",
    "batchNumber": "",
    "expiryDate": null,
    "mrp": 0,
    "quantity": 0
  },
  {
    "name": "A-Cal",
    "genericName": "Calcium Carbonate",
    "strength": "500 mg",
    "manufacturer": "ACME Laboratories Ltd.",
    "brand": "ACME",
    "category": "Calcium Supplement",
    "batchNumber": "",
    "expiryDate": null,
    "mrp": 0,
    "quantity": 0
  },
  {
    "name": "A-Cal D",
    "genericName": "Elemental Calcium + Vitamin D3",
    "strength": "500 mg + 200 IU",
    "manufacturer": "ACME Laboratories Ltd.",
    "brand": "ACME",
    "category": "Calcium Supplement",
    "batchNumber": "",
    "expiryDate": null,
    "mrp": 0,
    "quantity": 0
  },
  {
    "name": "A-Cal DX",
    "genericName": "Elemental Calcium + Vitamin D3",
    "strength": "500 mg + 400 IU",
    "manufacturer": "ACME Laboratories Ltd.",
    "brand": "ACME",
    "category": "Calcium Supplement",
    "batchNumber": "",
    "expiryDate": null,
    "mrp": 0,
    "quantity": 0
  },
  {
    "name": "A-Calm",
    "genericName": "Tolperisone Hydrochloride",
    "strength": "50 mg",
    "manufacturer": "ACME Laboratories Ltd.",
    "brand": "ACME",
    "category": "Muscle Relaxant",
    "batchNumber": "",
    "expiryDate": null,
    "mrp": 0,
    "quantity": 0
  },
  {
    "name": "A-Card",
    "genericName": "Isosorbide Mononitrate",
    "strength": "20 mg",
    "manufacturer": "ACME Laboratories Ltd.",
    "brand": "ACME",
    "category": "Cardiac Drug",
    "batchNumber": "",
    "expiryDate": null,
    "mrp": 0,
    "quantity": 0
  },
  {
    "name": "A-Care",
    "genericName": "Betacarotene + Vitamin C + Vitamin E",
    "strength": "6 mg + 200 mg + 50 mg",
    "manufacturer": "Asiatic Laboratories Ltd.",
    "brand": "Asiatic",
    "category": "Vitamin",
    "batchNumber": "",
    "expiryDate": null,
    "mrp": 0,
    "quantity": 0
  },
  {
    "name": "A-Clox 500 mg",
    "genericName": "Cloxacillin Sodium",
    "strength": "500 mg",
    "manufacturer": "ACME Laboratories Ltd.",
    "brand": "ACME",
    "category": "Antibiotic",
    "batchNumber": "",
    "expiryDate": null,
    "mrp": 0,
    "quantity": 0
  },
  {
    "name": "A-Clox 125 mg/5 ml",
    "genericName": "Cloxacillin Sodium",
    "strength": "125 mg/5 ml",
    "manufacturer": "ACME Laboratories Ltd.",
    "brand": "ACME",
    "category": "Antibiotic",
    "batchNumber": "",
    "expiryDate": null,
    "mrp": 0,
    "quantity": 0
  },
  {
    "name": "A-Clox 250 mg/vial",
    "genericName": "Cloxacillin Sodium",
    "strength": "250 mg/vial",
    "manufacturer": "ACME Laboratories Ltd.",
    "brand": "ACME",
    "category": "Antibiotic",
    "batchNumber": "",
    "expiryDate": null,
    "mrp": 0,
    "quantity": 0
  },
  {
    "name": "A-Clox 500 mg/vial",
    "genericName": "Cloxacillin Sodium",
    "strength": "500 mg/vial",
    "manufacturer": "ACME Laboratories Ltd.",
    "brand": "ACME",
    "category": "Antibiotic",
    "batchNumber": "",
    "expiryDate": null,
    "mrp": 0,
    "quantity": 0
  },
  {
    "name": "A-Cof (10 mg+30 mg+1.25 mg)/5 ml",
    "genericName": "Dextromethorphan + Pseudoephedrine + Triprolidine",
    "strength": "10 mg + 30 mg + 1.25 mg / 5 ml",
    "manufacturer": "ACME Laboratories Ltd.",
    "brand": "ACME",
    "category": "Cough Syrup",
    "batchNumber": "",
    "expiryDate": null,
    "mrp": 0,
    "quantity": 0
  },
  {
    "name": "A-Cold 4 mg/5 ml",
    "genericName": "Bromhexine Hydrochloride",
    "strength": "4 mg/5 ml",
    "manufacturer": "ACME Laboratories Ltd.",
    "brand": "ACME",
    "category": "Cough Syrup",
    "batchNumber": "",
    "expiryDate": null,
    "mrp": 0,
    "quantity": 0
  },
  {
    "name": "A-Fenac 25 mg",
    "genericName": "Diclofenac Sodium",
    "strength": "25 mg",
    "manufacturer": "ACME Laboratories Ltd.",
    "brand": "ACME",
    "category": "Painkiller",
    "batchNumber": "",
    "expiryDate": null,
    "mrp": 0,
    "quantity": 0
  },
  {
    "name": "A-Fenac 50 mg",
    "genericName": "Diclofenac Sodium",
    "strength": "50 mg",
    "manufacturer": "ACME Laboratories Ltd.",
    "brand": "ACME",
    "category": "Painkiller",
    "batchNumber": "",
    "expiryDate": null,
    "mrp": 0,
    "quantity": 0
  },
  {
    "name": "A-Fenac 75 mg/3 ml",
    "genericName": "Diclofenac Sodium",
    "strength": "75 mg/3 ml",
    "manufacturer": "ACME Laboratories Ltd.",
    "brand": "ACME",
    "category": "Painkiller",
    "batchNumber": "",
    "expiryDate": null,
    "mrp": 0,
    "quantity": 0
  },
  {
    "name": "A-Fenac 12.5 mg",
    "genericName": "Diclofenac Sodium",
    "strength": "12.5 mg",
    "manufacturer": "ACME Laboratories Ltd.",
    "brand": "ACME",
    "category": "Painkiller",
    "batchNumber": "",
    "expiryDate": null,
    "mrp": 0,
    "quantity": 0
  },
  {
    "name": "A-Fenac 1% w/w",
    "genericName": "Diclofenac Sodium",
    "strength": "1% w/w",
    "manufacturer": "ACME Laboratories Ltd.",
    "brand": "ACME",
    "category": "Pain Relief Gel",
    "batchNumber": "",
    "expiryDate": null,
    "mrp": 0,
    "quantity": 0
  },
  {
    "name": "A-Fenac K 50 mg",
    "genericName": "Diclofenac Potassium",
    "strength": "50 mg",
    "manufacturer": "ACME Laboratories Ltd.",
    "brand": "ACME",
    "category": "Painkiller",
    "batchNumber": "",
    "expiryDate": null,
    "mrp": 0,
    "quantity": 0
  },
  {
    "name": "A-Fenac Plus (75 mg+20 mg)/2 ml",
    "genericName": "Diclofenac Sodium + Lidocaine Hydrochloride",
    "strength": "75 mg + 20 mg / 2 ml",
    "manufacturer": "ACME Laboratories Ltd.",
    "brand": "ACME",
    "category": "Painkiller Injection",
    "batchNumber": "",
    "expiryDate": null,
    "mrp": 0,
    "quantity": 0
  },
  {
    "name": "A-Fenac SR 100 mg",
    "genericName": "Diclofenac Sodium",
    "strength": "100 mg",
    "manufacturer": "ACME Laboratories Ltd.",
    "brand": "ACME",
    "category": "Painkiller",
    "batchNumber": "",
    "expiryDate": null,
    "mrp": 0,
    "quantity": 0
  },
  {
    "name": "A-Flox 250 mg",
    "genericName": "Flucloxacillin Sodium",
    "strength": "250 mg",
    "manufacturer": "ACME Laboratories Ltd.",
    "brand": "ACME",
    "category": "Antibiotic",
    "batchNumber": "",
    "expiryDate": null,
    "mrp": 0,
    "quantity": 0
  },
  {
    "name": "A-Flox 500 mg",
    "genericName": "Flucloxacillin Sodium",
    "strength": "500 mg",
    "manufacturer": "ACME Laboratories Ltd.",
    "brand": "ACME",
    "category": "Antibiotic",
    "batchNumber": "",
    "expiryDate": null,
    "mrp": 0,
    "quantity": 0
  },
  {
    "name": "A-Flox 125 mg/5 ml",
    "genericName": "Flucloxacillin Sodium",
    "strength": "125 mg / 5 ml",
    "manufacturer": "ACME Laboratories Ltd.",
    "brand": "ACME",
    "category": "Antibiotic Syrup",
    "batchNumber": "",
    "expiryDate": null,
    "mrp": 0,
    "quantity": 0
  },
  {
    "name": "A-Flox 500 mg/vial",
    "genericName": "Flucloxacillin Sodium",
    "strength": "500 mg/vial",
    "manufacturer": "ACME Laboratories Ltd.",
    "brand": "ACME",
    "category": "Antibiotic Injection",
    "batchNumber": "",
    "expiryDate": null,
    "mrp": 0,
    "quantity": 0
  },
  {
    "name": "A-Forte 50000 IU",
    "genericName": "Vitamin A",
    "strength": "50000 IU",
    "manufacturer": "Globe Pharmaceuticals Ltd.",
    "brand": "Globe",
    "category": "Vitamin",
    "batchNumber": "",
    "expiryDate": null,
    "mrp": 0,
    "quantity": 0
  },
  {
    "name": "A-Kit 200 mg+200 mcg",
    "genericName": "Mifepristone + Misoprostol",
    "strength": "200 mg + 200 mcg",
    "manufacturer": "ACME Laboratories Ltd.",
    "brand": "ACME",
    "category": "Abortifacient",
    "batchNumber": "",
    "expiryDate": null,
    "mrp": 0,
    "quantity": 0
  },
  {
    "name": "A-Meb 135 mg",
    "genericName": "Mebeverine Hydrochloride",
    "strength": "135 mg",
    "manufacturer": "ACME Laboratories Ltd.",
    "brand": "ACME",
    "category": "Antispasmodic",
    "batchNumber": "",
    "expiryDate": null,
    "mrp": 0,
    "quantity": 0
  },
  {
    "name": "A-Mectin 6 mg",
    "genericName": "Ivermectin",
    "strength": "6 mg",
    "manufacturer": "ACME Laboratories Ltd.",
    "brand": "ACME",
    "category": "Antiparasitic",
    "batchNumber": "",
    "expiryDate": null,
    "mrp": 0,
    "quantity": 0
  }



]
